nisa_di/__init__.py
nisa_di/collection/__init__.py
nisa_di/collection/cache.py
nisa_di/context_inject.py
nisa_di/inject.py
nisa_di/locked_dict.py
nisa_di-0.6.0.dist-info/LICENSE
nisa_di-0.6.0.dist-info/WHEEL
nisa_di-0.6.0.dist-info/METADATA
nisa_di-0.6.0.dist-info/RECORD
