Metadata-Version: 2.1
Name: nisa-di
Version: 0.6.0
Summary: nisa dependencies injection pure python
Author: vaziria
Author-email: manorder123@gmail.com
Requires-Python: >=3.9,<4.0
Classifier: Programming Language :: Python :: 3
Classifier: Programming Language :: Python :: 3.10
Classifier: Programming Language :: Python :: 3.9
